LICENSE
README.md
setup.cfg
setup.py
imhotep/__init__.py
imhotep/app.py
imhotep/app_test.py
imhotep/diff_parser.py
imhotep/diff_parser_test.py
imhotep/errors.py
imhotep/http_client.py
imhotep/http_client_test.py
imhotep/integration_test.py
imhotep/main.py
imhotep/main_test.py
imhotep/repomanagers.py
imhotep/repomanagers_test.py
imhotep/repositories.py
imhotep/repositories_test.py
imhotep/shas.py
imhotep/shas_test.py
imhotep/testing_utils.py
imhotep/tools.py
imhotep/tools_test.py
imhotep.egg-info/PKG-INFO
imhotep.egg-info/SOURCES.txt
imhotep.egg-info/dependency_links.txt
imhotep.egg-info/entry_points.txt
imhotep.egg-info/requires.txt
imhotep.egg-info/top_level.txt
imhotep/regression_tests/__init__.py
imhotep/regression_tests/test_25.py
imhotep/reporters/__init__.py
imhotep/reporters/github.py
imhotep/reporters/printing.py
imhotep/reporters/reporter.py
imhotep/reporters/reporters_test.py